dicomp/__init__.py
dicomp/client.py
dicomp/component.py
dicomp/const.py
dicomp/dpy_overrides.py
dicomp/http.py
dicomp/interaction.py
dicomp/utils.py
dicomp-0.0.1.dist-info/METADATA
dicomp-0.0.1.dist-info/WHEEL
dicomp-0.0.1.dist-info/top_level.txt
dicomp-0.0.1.dist-info/RECORD
