Metadata-Version: 2.1
Name: dicomp
Version: 0.0.1
Summary: This is a project developed by Serem for development purposes
Home-page: https://github.com/hayul0629/wdex
Author: serem
Author-email: gangh9230@gmail.com
Classifier: Programming Language :: Python :: 3.6
Classifier: Programming Language :: Python :: 3.7
Classifier: Programming Language :: Python :: 3.8
Classifier: Programming Language :: Python :: 3.9
Requires-Python: >=3.9
Requires-Dist: novus ==0.2.3
Requires-Dist: nextcord
